{
    "cluster_id": 181,
    "variants": [
        {
            "id": 1197,
            "name_de": "Chair in Measurement Technology (CMT), Fachbereich Elektrotechnik/Informatik, Universität Kassel, Wilhelmshöher Allee 71, 34121 Kassel, Deutschland",
            "author_count": 2
        },
        {
            "id": 1488,
            "name_de": "Lehrstuhl für Messtechnik, Fachbereich Elektrotechnik/Informatik, Universität Kassel, Wilhelmshöher Allee 71, 34121 Kassel, Deutschland",
            "author_count": 1
        }
    ]
}