{
    "cluster_id": 146,
    "variants": [
        {
            "id": 867,
            "name_de": "Dept. Microsystems Eng. - IMTEK, Univ. Freiburg, Georges-Koehler-Allee 103, 79110 Freiburg",
            "author_count": 2
        },
        {
            "id": 1373,
            "name_de": "Laboratory for Chemistry and Physics of Interfaces, Department of Microsystems Engineering - IMTEK\nUniversity of Freiburg",
            "author_count": 1
        },
        {
            "id": 1478,
            "name_de": "Laboratory for Process Technology, IMTEK, Department of Microsystems Engineering, University of Freiburg, Georges-Koehler-Allee 103, 79110 Freiburg, Germany",
            "author_count": 2
        }
    ]
}