{
  "verdict": "keep_separate",
  "confidence": 0.88,
  "groups": [
    [144, 145, 436, 687, 1182, 1563],
    [135, 295, 815, 817],
    [674],
    [816, 895, 903],
    [905],
    [1360],
    [1599],
    [1708],
    [195]
  ],
  "canonical": [
    {
      "name_de": "Institut für Angewandte Physik, Westfälische Wilhelms-Universität Münster",
      "name_en": "Institute of Applied Physics, University of Münster",
      "kuerzel": "IAP",
      "universitaet": "Westfälische Wilhelms-Universität Münster",
      "ort": "Münster",
      "land": "DE",
      "ror_id": null
    },
    {
      "name_de": "Biomedizinisches Technologiezentrum, Medizinische Fakultät, Westfälische Wilhelms-Universität Münster",
      "name_en": "Biomedical Technology Center, Medical Faculty, University of Münster",
      "kuerzel": "BMTZ",
      "universitaet": "Westfälische Wilhelms-Universität Münster",
      "ort": "Münster",
      "land": "DE",
      "ror_id": null
    },
    {
      "name_de": "Institut für Hygiene, Westfälische Wilhelms-Universität Münster",
      "name_en": "Institute of Hygiene, University of Münster",
      "kuerzel": null,
      "universitaet": "Westfälische Wilhelms-Universität Münster",
      "ort": "Münster",
      "land": "DE",
      "ror_id": null
    },
    {
      "name_de": "Medizinische Kliniken und Polikliniken B und D, Westfälische Wilhelms-Universität Münster",
      "name_en": "Medical Clinics B and D, University of Münster",
      "kuerzel": null,
      "universitaet": "Westfälische Wilhelms-Universität Münster",
      "ort": "Münster",
      "land": "DE",
      "ror_id": null
    },
    {
      "name_de": "Institut für Zoologie und Genetik, Westfälische Wilhelms-Universität Münster",
      "name_en": "Institute of Zoology and Genetics, University of Münster",
      "kuerzel": null,
      "universitaet": "Westfälische Wilhelms-Universität Münster",
      "ort": "Münster",
      "land": "DE",
      "ror_id": null
    },
    {
      "name_de": "Institut für Physikalische Chemie, Westfälische Wilhelms-Universität Münster",
      "name_en": "Institute of Physical Chemistry, University of Münster",
      "kuerzel": null,
      "universitaet": "Westfälische Wilhelms-Universität Münster",
      "ort": "Münster",
      "land": "DE",
      "ror_id": null
    },
    {
      "name_de": "Institut für Theoretische Physik, Westfälische Wilhelms-Universität Münster",
      "name_en": "Institute of Theoretical Physics, University of Münster",
      "kuerzel": null,
      "universitaet": "Westfälische Wilhelms-Universität Münster",
      "ort": "Münster",
      "land": "DE",
      "ror_id": null
    },
    {
      "name_de": "Klinik für Augenheilkunde, Universitätsklinikum Münster",
      "name_en": "Department of Ophthalmology, University Hospital Münster",
      "kuerzel": null,
      "universitaet": "Westfälische Wilhelms-Universität Münster",
      "ort": "Münster",
      "land": "DE",
      "ror_id": null
    },
    {
      "name_de": "Labor für Biophysik, Westfälische Wilhelms-Universität Münster",
      "name_en": "Laboratory of Biophysics, University of Münster",
      "kuerzel": null,
      "universitaet": "Westfälische Wilhelms-Universität Münster",
      "ort": "Münster",
      "land": "DE",
      "ror_id": null
    }
  ],
  "reason": "Dieser Cluster enthält 9 distinct Sub-Institute und Kliniken der WWU Münster (ROR 00pd74e08), die alle an derselben Universität sind, aber völlig verschiedene Fachgebiete abdecken (Angewandte Physik, Biomedizin, Hygiene, Kliniken, Zoologie, Physikalische Chemie, Theoretische Physik, Augenheilkunde, Biophysik). Sub-Institute einer Universität → keep_separate gemäß Regel."
}
