{
  "verdict": "merge",
  "confidence": 0.97,
  "groups": [[1284, 1613]],
  "canonical": [
    {
      "name_de": "VTT Technical Research Centre of Finland",
      "name_en": "VTT Technical Research Centre of Finland",
      "kuerzel": "VTT",
      "universitaet": "",
      "ort": "Oulu / Espoo",
      "land": "FI",
      "ror_id": "https://ror.org/04b181w54"
    }
  ],
  "reason": "Beide Einträge bezeichnen dieselbe Organisation VTT Technical Research Centre of Finland: einmal mit Adressangabe (Oulu-Standort) und einmal in Kurzform mit \"Ltd\"-Zusatz nach der Umfirmierung 2015. Reine Schreibvarianten – merge."
}
