{
  "verdict": "merge",
  "confidence": 0.98,
  "groups": [
    [31, 1290]
  ],
  "canonical": [
    {
      "name_de": "Fakultät Optik und Mechatronik",
      "name_en": "Faculty of Optics and Mechatronics",
      "kuerzel": "",
      "universitaet": "Hochschule Aalen",
      "ort": "Aalen",
      "land": "DE",
      "ror_id": "https://ror.org/04gg60e72"
    }
  ],
  "reason": "Beide Varianten bezeichnen dieselbe Fakultät Optik und Mechatronik an der Hochschule Aalen — einmal mit und einmal ohne vollständige Adresse."
}
